vlod/__init__.py
vlod/__main__.py
VLoD_Validater_Package-1.0.0.dist-info/METADATA
VLoD_Validater_Package-1.0.0.dist-info/WHEEL
VLoD_Validater_Package-1.0.0.dist-info/top_level.txt
VLoD_Validater_Package-1.0.0.dist-info/RECORD
